{
  "sections": {
    "1643907509c016666d": {
      "type": "custom-banner",
      "settings": {
        "background_image": "shopify:\/\/shop_images\/gift-wrapped-with-bow.jpg",
        "title": "Formatos Presentation Regalos",
        "description": "",
        "height": "300px"
      }
    },
    "16443085546572c4cc": {
      "type": "custom-multicolumn",
      "blocks": {
        "1644308554b34dc7a4-0": {
          "type": "column",
          "settings": {
            "image": "shopify:\/\/shop_images\/265668804_487957076023812_5407824488742590208_n.jpg",
            "title": "",
            "text": "<p>Y a quien no le gusta que le regalen y le conquistan por el estomago?Este es nuestro \"buque insignia’ , es el formato con el que nos dimos a conocer y con el quemas cOmodos nos sentimos, en una palabra “nuestro primer hijo’. Aparecio por la necesidad de unir REGALO con PRODUCTO DE LA TIERRA y poco a poco nuestros clientes (algunos ya amigos) fueron confidndonos sus deseos de querer hacer llegar esos detalles bonitos a sus personas queridas y que pudieran disfrutar de ellos.Unir REGALO ,CARINO Y PRODUCTO LOCAL es sinonimo de ACIERTO SEGURO.\"Que alguien piense que eres especial es el mejor de los regalos; tu lo eres...DISFRUTALO \"<\/p>",
            "link_label": "Cajas",
            "link": ""
          }
        },
        "1644308554b34dc7a4-1": {
          "type": "column",
          "settings": {
            "image": "shopify:\/\/shop_images\/peron-holds-white-paper-bags-in-both-hands.jpg",
            "title": "",
            "text": "<p>Verdad que siempre pensamos en que detalle regalar y ademas quedar como reyes?Pues esta seccion te ofrece ese detalle bonito en forma de regalo pero no por ello menosimportante, porque ponemos todo el carino y metemos dentro de cada bolsa el sabor de lo nuestro.Detalle comodo, donde te damos opciones varias o incluso la oportunidad que crees la tuya propia y nosotros nos encargamos de ponerla bonita y que lleve parte de nuestra ESENCIA.*variedad de productos especiales eventos. * tarjetas de personalizacion. *empaquetado especial para cada evento(preguntar presupuesto). *personalizamos todos tus detalles.<\/p>",
            "link_label": "",
            "link": ""
          }
        },
        "1644308554b34dc7a4-2": {
          "type": "column",
          "settings": {
            "image": "shopify:\/\/shop_images\/teal-gift-wrap-with-white-ribbon.jpg",
            "title": "",
            "text": "<p>Lorem ipsum dolor sit amet, consectetur adipiscing elit, sed do eiusmod tempor incididunt ut labore et dolore magna aliqua. Ut enim ad minim veniam, quis nostrud exercitation ullamco laboris nisi ut aliquip ex ea commodo consequat<\/p>",
            "link_label": "",
            "link": ""
          }
        }
      },
      "block_order": [
        "1644308554b34dc7a4-0",
        "1644308554b34dc7a4-1",
        "1644308554b34dc7a4-2"
      ],
      "settings": {
        "image_height": "400px",
        "grid_template_columns": "auto auto auto",
        "grid_template_columns_mobile": "auto auto",
        "grid_gap": "20px",
        "has_border": false
      }
    },
    "16430557592e7638cd": {
      "type": "multicolumn",
      "blocks": {
        "1643055759d7123ab7-0": {
          "type": "column",
          "settings": {
            "image": "shopify:\/\/shop_images\/portrait-of-boxes-and-packages.jpg",
            "title": "",
            "text": "<p>Y a quien no le gusta que le regalen y le conquistan por el estomago?Este es nuestro \"buque insignia’ , es el formato con el que nos dimos a conocer y con el quemas cOmodos nos sentimos, en una palabra “nuestro primer hijo’. Aparecio por la necesidad de unir REGALO con PRODUCTO DE LA TIERRA y poco a poco nuestros clientes (algunos ya amigos) fueron confidndonos sus deseos de querer hacer llegar esos detalles bonitos a sus personas queridas y que pudieran disfrutar de ellos.Unir REGALO ,CARINO Y PRODUCTO LOCAL es sinonimo de ACIERTO SEGURO.\"Que alguien piense que eres especial es el mejor de los regalos; tu lo eres...DISFRUTALO \"<\/p>",
            "link_label": "Cajas",
            "link": "shopify:\/\/collections\/regalos-formatos-caja"
          }
        },
        "1643055759d7123ab7-1": {
          "type": "column",
          "settings": {
            "image": "shopify:\/\/shop_images\/blue-yellow-gift-wrap.jpg",
            "title": "",
            "text": "<p>Verdad que siempre pensamos en que detalle regalar y ademas quedar como reyes?Pues esta seccion te ofrece ese detalle bonito en forma de regalo pero no por ello menosimportante, porque ponemos todo el carino y metemos dentro de cada bolsa el sabor de lo nuestro.Detalle comodo, donde te damos opciones varias o incluso la oportunidad que crees la tuya propia y nosotros nos encargamos de ponerla bonita y que lleve parte de nuestra ESENCIA.*variedad de productos especiales eventos. * tarjetas de personalizacion. *empaquetado especial para cada evento(preguntar presupuesto). *personalizamos todos tus detalles.<\/p>",
            "link_label": "Bolzas",
            "link": "shopify:\/\/collections\/regalos-formatos-bolzas"
          }
        },
        "1643055759d7123ab7-2": {
          "type": "column",
          "settings": {
            "image": "shopify:\/\/shop_images\/holiday-gift-wrapping.jpg",
            "title": "Otros",
            "text": "<p>Lorem ipsum dolor sit amet, consectetur adipiscing elit, sed do eiusmod tempor incididunt ut labore et dolore magna aliqua. Ut enim ad minim veniam, quis nostrud exercitation ullamco laboris nisi ut aliquip ex ea commodo consequat.<\/p>",
            "link_label": "Otros",
            "link": "shopify:\/\/collections\/regalos-formatos-otros"
          }
        }
      },
      "block_order": [
        "1643055759d7123ab7-0",
        "1643055759d7123ab7-1",
        "1643055759d7123ab7-2"
      ],
      "settings": {
        "title": "",
        "image_width": "full",
        "image_ratio": "adapt",
        "column_alignment": "left",
        "background_style": "primary",
        "button_label": "",
        "button_link": "",
        "swipe_on_mobile": false,
        "color_scheme": "background-1",
        "padding_top": 36,
        "padding_bottom": 36
      }
    },
    "main": {
      "type": "main-page",
      "disabled": true,
      "settings": {
      }
    }
  },
  "order": [
    "1643907509c016666d",
    "16443085546572c4cc",
    "16430557592e7638cd",
    "main"
  ]
}
